CHANGES.txt
README.txt
bootstrap.py
buildout.cfg
setup.py
src/zope/__init__.py
src/zope.app.fssync.egg-info/PKG-INFO
src/zope.app.fssync.egg-info/SOURCES.txt
src/zope.app.fssync.egg-info/dependency_links.txt
src/zope.app.fssync.egg-info/namespace_packages.txt
src/zope.app.fssync.egg-info/not-zip-safe
src/zope.app.fssync.egg-info/requires.txt
src/zope.app.fssync.egg-info/top_level.txt
src/zope/app/__init__.py
src/zope/app/fssync/DEPENDENCIES.cfg
src/zope/app/fssync/SETUP.cfg
src/zope/app/fssync/__init__.py
src/zope/app/fssync/application.zcml
src/zope/app/fssync/command.py
src/zope/app/fssync/configure.zcml
src/zope/app/fssync/demo_server.py
src/zope/app/fssync/fsmerge.txt
src/zope/app/fssync/fspickle.py
src/zope/app/fssync/fspickle.txt
src/zope/app/fssync/fssite.txt
src/zope/app/fssync/fssync.py
src/zope/app/fssync/fssync.txt
src/zope/app/fssync/ftesting.zcml
src/zope/app/fssync/ftests.py
src/zope/app/fssync/main.py
src/zope/app/fssync/merge.py
src/zope/app/fssync/merge.txt
src/zope/app/fssync/passwd.py
src/zope/app/fssync/security.txt
src/zope/app/fssync/ssh.py
src/zope/app/fssync/syncer.py
src/zope/app/fssync/testing.py
src/zope/app/fssync/zope.app.fssync-configure.zcml
src/zope/app/fssync/browser/__init__.py
src/zope/app/fssync/browser/configure.zcml
src/zope/app/fssync/browser/fromFS.pt
src/zope/app/fssync/dtmlpage/DEPENDENCIES.cfg
src/zope/app/fssync/dtmlpage/SETUP.cfg
src/zope/app/fssync/dtmlpage/__init__.py
src/zope/app/fssync/dtmlpage/adapter.py
src/zope/app/fssync/dtmlpage/configure.zcml
src/zope/app/fssync/dtmlpage/zope.app.fssync.dtmlpage-configure.zcml
src/zope/app/fssync/dublincore/DEPENDENCIES.cfg
src/zope/app/fssync/dublincore/SETUP.cfg
src/zope/app/fssync/dublincore/__init__.py
src/zope/app/fssync/dublincore/adapter.py
src/zope/app/fssync/dublincore/configure.zcml
src/zope/app/fssync/dublincore/zope.app.fssync.dublincore-configure.zcml
src/zope/app/fssync/file/DEPENDENCIES.cfg
src/zope/app/fssync/file/SETUP.cfg
src/zope/app/fssync/file/__init__.py
src/zope/app/fssync/file/adapter.py
src/zope/app/fssync/file/configure.zcml
src/zope/app/fssync/file/tests.py
src/zope/app/fssync/file/zope.app.fssync.file-configure.zcml
src/zope/app/fssync/folder/DEPENDENCIES.cfg
src/zope/app/fssync/folder/SETUP.cfg
src/zope/app/fssync/folder/__init__.py
